print_fa/__init__.py
print_fa/print_fa.py
print_fa-0.1.0.dist-info/licenses/LICENSE
print_fa-0.1.0.dist-info/METADATA
print_fa-0.1.0.dist-info/WHEEL
print_fa-0.1.0.dist-info/top_level.txt
print_fa-0.1.0.dist-info/RECORD
