Metadata-Version: 2.4
Name: print_fa
Version: 0.1.0
Summary: A Python library for correct printing of Persian (Farsi) text with RTL support and styling options.
Home-page: https://github.com/httex/print_fa
Author: httex
Author-email: your.email@example.com
Classifier: Programming Language :: Python :: 3
Classifier: License :: OSI Approved :: MIT License
Classifier: Operating System :: OS Independent
Classifier: Development Status :: 3 - Alpha
Classifier: Intended Audience :: Developers
Classifier: Topic :: Software Development :: Libraries :: Python Modules
Classifier: Topic :: Text Processing :: General
Classifier: Natural Language :: Persian
Requires-Python: >=3.6
License-File: LICENSE
Requires-Dist: arabic-reshaper
Requires-Dist: python-bidi
Dynamic: author
Dynamic: author-email
Dynamic: classifier
Dynamic: description
Dynamic: description-content-type
Dynamic: home-page
Dynamic: license-file
Dynamic: requires-dist
Dynamic: requires-python
Dynamic: summary
